CHANGES.txt
CONTRIBUTORS.txt
README.txt
bootstrap.py
buildout.cfg
setup.py
plone/__init__.py
plone.recipe.osxcontroller.egg-info/PKG-INFO
plone.recipe.osxcontroller.egg-info/SOURCES.txt
plone.recipe.osxcontroller.egg-info/dependency_links.txt
plone.recipe.osxcontroller.egg-info/entry_points.txt
plone.recipe.osxcontroller.egg-info/namespace_packages.txt
plone.recipe.osxcontroller.egg-info/not-zip-safe
plone.recipe.osxcontroller.egg-info/requires.txt
plone.recipe.osxcontroller.egg-info/top_level.txt
plone/recipe/__init__.py
plone/recipe/osxcontroller/README.txt
plone/recipe/osxcontroller/__init__.py
plone/recipe/osxcontroller/PloneController.app/icon.bin
plone/recipe/osxcontroller/PloneController.app/Contents/Info.plist
plone/recipe/osxcontroller/PloneController.app/Contents/PkgInfo
plone/recipe/osxcontroller/PloneController.app/Contents/MacOS/PloneController
plone/recipe/osxcontroller/PloneController.app/Contents/MacOS/Python
plone/recipe/osxcontroller/PloneController.app/Contents/Resources/Notebook.py
plone/recipe/osxcontroller/PloneController.app/Contents/Resources/PloneController.py
plone/recipe/osxcontroller/PloneController.app/Contents/Resources/aboutDialog.py
plone/recipe/osxcontroller/PloneController.app/Contents/Resources/config.py
plone/recipe/osxcontroller/PloneController.app/Contents/Resources/configPage.py
plone/recipe/osxcontroller/PloneController.app/Contents/Resources/guageApp.py
plone/recipe/osxcontroller/PloneController.app/Contents/Resources/plone.icns
plone/recipe/osxcontroller/PloneController.app/Contents/Resources/states.py
plone/recipe/osxcontroller/PloneController.app/Contents/Resources/status.py
plone/recipe/osxcontroller/PloneController.app/Contents/Resources/statusPage.py
plone/recipe/osxcontroller/PloneController.app/Contents/Resources/statusPosix.py
plone/recipe/osxcontroller/PloneController.app/Contents/Resources/version.txt
plone/recipe/osxcontroller/PloneController.app/Contents/Resources/webBrowser.py
plone/recipe/osxcontroller/PloneController.app/Contents/Resources/images/plone-icon.png
plone/recipe/osxcontroller/tests/__init__.py
plone/recipe/osxcontroller/tests/test_docs.py