Metadata-Version: 1.0
Name: plone.recipe.osxcontroller
Version: 0.4
Summary: Installs a wxPython-based Plone controller for OS X
Home-page: http://plone.org/
Author: Steve McMahon
Author-email: steve@dcn.org
License: GPL
Keywords: plone
Platform: UNKNOWN
Classifier: Framework :: Buildout
Classifier: Topic :: Software Development :: Build Tools
Classifier: Topic :: Software Development :: Libraries :: Python Modules
Classifier: License :: OSI Approved :: Zope Public License
